pyfan/__init__.py
pyfan/amto/__init__.py
pyfan/amto/array/__init__.py
pyfan/amto/array/geomspace.py
pyfan/amto/array/gridminmax.py
pyfan/amto/array/mesh.py
pyfan/amto/array/scalararray.py
pyfan/amto/json/__init__.py
pyfan/amto/json/json.py
pyfan/amto/lsdc/__init__.py
pyfan/amto/lsdc/lsdcconvert.py
pyfan/amto/numeric/__init__.py
pyfan/amto/numeric/round.py
pyfan/aws/__init__.py
pyfan/aws/general/__init__.py
pyfan/aws/general/credentials.py
pyfan/aws/general/path.py
pyfan/aws/s3/__init__.py
pyfan/aws/s3/pushsync.py
pyfan/devel/__init__.py
pyfan/devel/flog/__init__.py
pyfan/devel/flog/logsupport.py
pyfan/devel/obj/__init__.py
pyfan/devel/obj/classobjsupport.py
pyfan/gen/__init__.py
pyfan/gen/rand/__init__.py
pyfan/gen/rand/randgrid.py
pyfan/graph/__init__.py
pyfan/graph/exa/__init__.py
pyfan/graph/exa/scatterline3.py
pyfan/graph/generic/__init__.py
pyfan/graph/generic/allpurpose.py
pyfan/graph/tools/__init__.py
pyfan/graph/tools/subplot.py
pyfan/panda/__init__.py
pyfan/panda/categorical/__init__.py
pyfan/panda/categorical/catevars.py
pyfan/panda/categorical/strsvarskeys.py
pyfan/panda/inout/__init__.py
pyfan/panda/inout/combine.py
pyfan/panda/inout/readexport.py
pyfan/panda/sandbox/sandbox.py
pyfan/panda/stats/__init__.py
pyfan/panda/stats/cutting.py
pyfan/panda/stats/mean_varcov.py
pyfan/panda/stats/polynomial_regression.py
pyfan/sandbox/sandbox_20200623.py
pyfan/sandbox/sandbox_20201105.py
pyfan/stats/__init__.py
pyfan/stats/interpolate/__init__.py
pyfan/stats/interpolate/interpolate2d.py
pyfan/stats/markov/__init__.py
pyfan/stats/markov/transprobcheck.py
pyfan/stats/multinomial/__init__.py
pyfan/stats/multinomial/multilogit.py
pyfan/table/__init__.py
pyfan/table/reg/__init__.py
pyfan/table/reg/txt2textab.py
pyfan/util/__init__.py
pyfan/util/inout/exportpanda.py
pyfan/util/inout/iosupport.py
pyfan/util/path/__init__.py
pyfan/util/path/getfiles.py
pyfan/util/path/movefiles.py
pyfan/util/pdf/__init__.py
pyfan/util/pdf/pdfgen.py
pyfan/util/rmd/__init__.py
pyfan-0.1.53.dist-info/LICENSE
pyfan-0.1.53.dist-info/METADATA
pyfan-0.1.53.dist-info/WHEEL
pyfan-0.1.53.dist-info/RECORD
